Workbook

Sheet Instructions
A1: Freight Business Tracking Logs
A3: How to use
A4: 1. Retailer Call Log: one row per retailer call (see docs/retailer-outreach-script.md).
A5: 2. Seller Lead Log: one row per software-found load you verify by phone (see docs/seller-phone-check-sheet.md).
A6: 3. Load Margin: one row per load; enter costs and buyer price, the margin calculates itself.
A7: 4. Dashboard: the numbers the advisor board asked for. It updates automatically.
A9: What to edit
A10: Type only in the log rows starting at row 3 (blue text = your inputs). Row 2 on each log is a grey EXAMPLE row; it is not counted. Overwrite or delete it if you like.
A11: Grey-headed columns marked 'calc' on Load Margin are formulas; do not type over them.
A12: Dropdown columns (Result, Available?, Decision, etc.) only accept the listed values.
A14: Targets (from the board): 20 retailer calls, 3-5 written commitments or deposits, 25%+ gross margin per load, under 30 days from purchase to sale.
A15: The example rows use made-up values. Formulas cover rows 3 to 502 on each log.

Sheet Dashboard
A1: Dashboard
A3: Retailer outreach (Target)
A4: Calls logged | B4: =COUNTA('Retailer Call Log'!B3:B502) | C4: 20
A5: Retailers who agreed to talk | B5: =COUNTA('Retailer Call Log'!B3:B502)-COUNTIF('Retailer Call Log'!I3:I502,"No answer")
A6: Talk rate | B6: =IFERROR(B5/B4,0)
A7: Written commitments (LOI) | B7: =COUNTIF('Retailer Call Log'!I3:I502,"LOI") | C7: 3-5 (LOI + deposits)
A8: Deposits | B8: =COUNTIF('Retailer Call Log'!I3:I502,"Deposit")
A9: Total commitments | B9: =B7+B8 | C9: 3-5
A11: Software accuracy (Target)
A12: Leads checked | B12: =COUNTA('Seller Lead Log'!A3:A502) | C12: 10+
A13: Hit rate (available) | B13: =IFERROR(COUNTIF('Seller Lead Log'!E3:E502,"Y")/B12,0) | C13: higher is better
A14: Clean rate (available, title OK, manifest + photos) | B14: =IFERROR(COUNTIFS('Seller Lead Log'!E3:E502,"Y",'Seller Lead Log'!F3:F502,"Y",'Seller Lead Log'!G3:G502,"Y")/B12,0)
A15: Go rate | B15: =IFERROR(COUNTIF('Seller Lead Log'!I3:I502,"Go")/B12,0)
A17: Load economics (Target)
A18: Loads closed | B18: =COUNT('Load Margin'!G3:G502) | C18: 3-5
A19: Average gross margin | B19: =IFERROR(AVERAGE('Load Margin'!I3:I502),0) | C19: 25%+
A20: Loads at or above margin target | B20: =COUNTIF('Load Margin'!K3:K502,"Yes")
A21: Average days to sale | B21: =IFERROR(AVERAGE('Load Margin'!J3:J502),0) | C21: under 30
A23: Formulas ignore the grey example rows (row 2 on each log).

Sheet Retailer Call Log
A1: Date | B1: Store | C1: Contact | D1: Category | E1: Size / price wanted | F1: Region | G1: Past problem | H1: Ask made | I1: Result | J1: Next step | K1: Next step date
A2: 2026-10-01 | B2: Example Discount Mart | C2: Pat Lee | D2: Household goods | E2: Pallets, ~30% of retail | F2: Ohio | G2: Damaged pallets from a broker | H2: LOI | I2: LOI | J2: Send example load Fri | K2: 2026-10-05

Sheet Seller Lead Log
A1: Load ID | B1: Date | C1: Seller | D1: Contact / phone | E1: Available? | F1: Title OK? | G1: Manifest + photos? | H1: Price ($) | I1: Decision | J1: Why dropped / notes
A2: L-001 | B2: 2026-10-01 | C2: Example Liquidation Co | D2: Sam, 555-0100 | E2: Y | F2: Y | G2: Y | H2: 4200 | I2: Go | J2: Example only

Sheet Load Margin
A1: Load ID | B1: Purchase price ($) | C1: Freight ($) | D1: Handling / storage ($) | E1: Insurance / fees ($) | F1: All-in cost ($) calc | G1: Buyer price ($) | H1: Gross profit ($) calc | I1: Gross margin calc | J1: Days purchase to sale | K1: Meets 25% target? calc
A2: L-001 | B2: 4200 | C2: 600 | D2: 150 | E2: 50 | F2: =IF(A2="","",SUM(B2:E2)) | G2: 7200 | H2: =IF(OR(A2="",G2=""),"",G2-F2) | I2: =IF(OR(A2="",G2="",G2=0),"",H2/G2) | J2: 18 | K2: =IF(I2="","",IF(I2>=$N$3,"Yes","No")) | M2: Assumptions
F3: =IF(A3="","",SUM(B3:E3)) | H3: =IF(OR(A3="",G3=""),"",G3-F3) | I3: =IF(OR(A3="",G3="",G3=0),"",H3/G3) | K3: =IF(I3="","",IF(I3>=$N$3,"Yes","No")) | M3: Margin target | N3: 0.25
F4: =IF(A4="","",SUM(B4:E4)) | H4: =IF(OR(A4="",G4=""),"",G4-F4) | I4: =IF(OR(A4="",G4="",G4=0),"",H4/G4) | K4: =IF(I4="","",IF(I4>=$N$3,"Yes","No")) | M4: Max days to sale | N4: 30
F5: =IF(A5="","",SUM(B5:E5)) | H5: =IF(OR(A5="",G5=""),"",G5-F5) | I5: =IF(OR(A5="",G5="",G5=0),"",H5/G5) | K5: =IF(I5="","",IF(I5>=$N$3,"Yes","No")) | M5: Source: targets set by the advisor board in this session.
F6: =IF(A6="","",SUM(B6:E6)) | H6: =IF(OR(A6="",G6=""),"",G6-F6) | I6: =IF(OR(A6="",G6="",G6=0),"",H6/G6) | K6: =IF(I6="","",IF(I6>=$N$3,"Yes","No"))
F7: =IF(A7="","",SUM(B7:E7)) | H7: =IF(OR(A7="",G7=""),"",G7-F7) | I7: =IF(OR(A7="",G7="",G7=0),"",H7/G7) | K7: =IF(I7="","",IF(I7>=$N$3,"Yes","No"))
F8: =IF(A8="","",SUM(B8:E8)) | H8: =IF(OR(A8="",G8=""),"",G8-F8) | I8: =IF(OR(A8="",G8="",G8=0),"",H8/G8) | K8: =IF(I8="","",IF(I8>=$N$3,"Yes","No"))
F9: =IF(A9="","",SUM(B9:E9)) | H9: =IF(OR(A9="",G9=""),"",G9-F9) | I9: =IF(OR(A9="",G9="",G9=0),"",H9/G9) | K9: =IF(I9="","",IF(I9>=$N$3,"Yes","No"))
F10: =IF(A10="","",SUM(B10:E10)) | H10: =IF(OR(A10="",G10=""),"",G10-F10) | I10: =IF(OR(A10="",G10="",G10=0),"",H10/G10) | K10: =IF(I10="","",IF(I10>=$N$3,"Yes","No"))
F11: =IF(A11="","",SUM(B11:E11)) | H11: =IF(OR(A11="",G11=""),"",G11-F11) | I11: =IF(OR(A11="",G11="",G11=0),"",H11/G11) | K11: =IF(I11="","",IF(I11>=$N$3,"Yes","No"))
F12: =IF(A12="","",SUM(B12:E12)) | H12: =IF(OR(A12="",G12=""),"",G12-F12) | I12: =IF(OR(A12="",G12="",G12=0),"",H12/G12) | K12: =IF(I12="","",IF(I12>=$N$3,"Yes","No"))
F13: =IF(A13="","",SUM(B13:E13)) | H13: =IF(OR(A13="",G13=""),"",G13-F13) | I13: =IF(OR(A13="",G13="",G13=0),"",H13/G13) | K13: =IF(I13="","",IF(I13>=$N$3,"Yes","No"))
F14: =IF(A14="","",SUM(B14:E14)) | H14: =IF(OR(A14="",G14=""),"",G14-F14) | I14: =IF(OR(A14="",G14="",G14=0),"",H14/G14) | K14: =IF(I14="","",IF(I14>=$N$3,"Yes","No"))
F15: =IF(A15="","",SUM(B15:E15)) | H15: =IF(OR(A15="",G15=""),"",G15-F15) | I15: =IF(OR(A15="",G15="",G15=0),"",H15/G15) | K15: =IF(I15="","",IF(I15>=$N$3,"Yes","No"))
F16: =IF(A16="","",SUM(B16:E16)) | H16: =IF(OR(A16="",G16=""),"",G16-F16) | I16: =IF(OR(A16="",G16="",G16=0),"",H16/G16) | K16: =IF(I16="","",IF(I16>=$N$3,"Yes","No"))
F17: =IF(A17="","",SUM(B17:E17)) | H17: =IF(OR(A17="",G17=""),"",G17-F17) | I17: =IF(OR(A17="",G17="",G17=0),"",H17/G17) | K17: =IF(I17="","",IF(I17>=$N$3,"Yes","No"))
... F502: =IF(A502="","",SUM(B502:E502)) | H502: =IF(OR(A502="",G502=""),"",G502-F502) | I502: =IF(OR(A502="",G502="",G502=0),"",H502/G502) | K502: =IF(I502="","",IF(I502>=$N$3,"Yes","No"))
